fedvision_deploy_toolkit/__init__.py
fedvision_deploy_toolkit/_build.py
fedvision_deploy_toolkit/_deploy.py
fedvision_deploy_toolkit/_generate_template.py
fedvision_deploy_toolkit/_service.py
fedvision_deploy_toolkit/cli.py
fedvision_deploy_toolkit/data/__init__.py
fedvision_deploy_toolkit/data/fedvision.tar.gz
fedvision_deploy_toolkit/template/__init__.py
fedvision_deploy_toolkit/template/standalone_template.yaml
fedvision_deploy_toolkit/template/template.yaml
fedvision_deploy_toolkit-0.2.dist-info/METADATA
fedvision_deploy_toolkit-0.2.dist-info/WHEEL
fedvision_deploy_toolkit-0.2.dist-info/entry_points.txt
fedvision_deploy_toolkit-0.2.dist-info/top_level.txt
fedvision_deploy_toolkit-0.2.dist-info/RECORD
